{
  "type": "collection.insomnia.rest/5.0",
  "name": "Scratch Pad",
  "meta": {
    "id": "wrk_e7e1aa9660f046f6a001075251564ee5",
    "created": 1746500190361,
    "modified": 1746500190361
  },
  "collection": [
    {
      "name": "Scratch Pad",
      "meta": {
        "id": "fld_87b8aa6608d74571be444462531b9697",
        "created": 1746500190363,
        "modified": 1746500433917,
        "sortKey": -1746500187461
      },
      "children": [
        {
          "url": "{{base_url}}/ping",
          "name": "Ping",
          "meta": {
            "id": "req_39fde39c73604ed68a7490c12dbd380e",
            "created": 1746500190368,
            "modified": 1746500389245,
            "isPrivate": false,
            "sortKey": -1746500187460
          },
          "method": "GET",
          "headers": [
            {
              "name": "User-Agent",
              "value": "insomnia/8.3.0"
            }
          ],
          "authentication": {
            "type": "bearer",
            "disabled": false,
            "token": "{{access_token}}"
          },
          "settings": {
            "renderRequestBody": true,
            "encodeUrl": true,
            "followRedirects": "global",
            "cookies": {
              "send": true,
              "store": true
            },
            "rebuildPath": true
          }
        },
        {
          "url": "{{base_url}}/person/list",
          "name": "FindAll",
          "meta": {
            "id": "req_288731ea22e745fab6116621c1eebbe8",
            "created": 1746500190369,
            "modified": 1746500190369,
            "isPrivate": false,
            "sortKey": -1746500187459
          },
          "method": "GET",
          "parameters": [
            {
              "disabled": true
            }
          ],
          "headers": [
            {
              "name": "User-Agent",
              "value": "insomnia/8.3.0"
            }
          ],
          "authentication": {
            "type": "bearer",
            "disabled": false,
            "token": "{{access_token}}"
          },
          "settings": {
            "renderRequestBody": true,
            "encodeUrl": true,
            "followRedirects": "global",
            "cookies": {
              "send": true,
              "store": true
            },
            "rebuildPath": true
          }
        },
        {
          "url": "{{base_url}}/person/findByFirstName/Max",
          "name": "FindByFirst -> OK",
          "meta": {
            "id": "req_79bfd7cacc5b481db85d2b668fe55b29",
            "created": 1746500190369,
            "modified": 1746500190369,
            "isPrivate": false,
            "sortKey": -1746500187458
          },
          "method": "GET",
          "parameters": [
            {
              "disabled": true
            }
          ],
          "headers": [
            {
              "name": "User-Agent",
              "value": "insomnia/8.3.0"
            }
          ],
          "authentication": {
            "type": "bearer",
            "disabled": false,
            "token": "{{access_token}}"
          },
          "settings": {
            "renderRequestBody": true,
            "encodeUrl": true,
            "followRedirects": "global",
            "cookies": {
              "send": true,
              "store": true
            },
            "rebuildPath": true
          }
        },
        {
          "url": "{{base_url}}/person/findByFirstName/Mustermann",
          "name": "FindByFirst -> NOT FOUND",
          "meta": {
            "id": "req_695d9b21e3a847dd861b9d065f877124",
            "created": 1746500190370,
            "modified": 1746500190370,
            "isPrivate": false,
            "sortKey": -1746500187457
          },
          "method": "GET",
          "headers": [
            {
              "name": "User-Agent",
              "value": "insomnia/8.3.0"
            }
          ],
          "authentication": {
            "type": "bearer",
            "disabled": false,
            "token": "{{access_token}}"
          },
          "settings": {
            "renderRequestBody": true,
            "encodeUrl": true,
            "followRedirects": "global",
            "cookies": {
              "send": true,
              "store": true
            },
            "rebuildPath": true
          }
        },
        {
          "url": "{{base_url}}/person/findByLastName/Max",
          "name": "FindByLast -> NOT FOUND",
          "meta": {
            "id": "req_29d12e69b50d4274a09709b1c3400da4",
            "created": 1746500190371,
            "modified": 1746500190371,
            "isPrivate": false,
            "sortKey": -1746500187455
          },
          "method": "GET",
          "parameters": [
            {
              "disabled": true
            }
          ],
          "headers": [
            {
              "name": "User-Agent",
              "value": "insomnia/8.3.0"
            }
          ],
          "authentication": {
            "type": "bearer",
            "disabled": false,
            "token": "{{access_token}}"
          },
          "settings": {
            "renderRequestBody": true,
            "encodeUrl": true,
            "followRedirects": "global",
            "cookies": {
              "send": true,
              "store": true
            },
            "rebuildPath": true
          }
        },
        {
          "url": "{{base_url}}/person/findByLastName/Mustermann",
          "name": "FindByLast -> OK",
          "meta": {
            "id": "req_ac4bf703f9f64d3086da18dd9fa0f062",
            "created": 1746500190371,
            "modified": 1746500190371,
            "isPrivate": false,
            "sortKey": -1746500187456
          },
          "method": "GET",
          "parameters": [
            {
              "disabled": true
            }
          ],
          "headers": [
            {
              "name": "User-Agent",
              "value": "insomnia/8.3.0"
            }
          ],
          "authentication": {
            "type": "bearer",
            "disabled": false,
            "token": "{{access_token}}"
          },
          "settings": {
            "renderRequestBody": true,
            "encodeUrl": true,
            "followRedirects": "global",
            "cookies": {
              "send": true,
              "store": true
            },
            "rebuildPath": true
          }
        },
        {
          "url": "{{base_url}}/person/findByNumber/0664123456789",
          "name": "FindByPhoneNumber -> OK",
          "meta": {
            "id": "req_e18a65668b5e49f59d1880392925584e",
            "created": 1746500190371,
            "modified": 1746500190371,
            "isPrivate": false,
            "sortKey": -1746500187454
          },
          "method": "GET",
          "parameters": [
            {
              "disabled": true
            }
          ],
          "headers": [
            {
              "name": "User-Agent",
              "value": "insomnia/8.3.0"
            }
          ],
          "authentication": {
            "type": "bearer",
            "disabled": false,
            "token": "{{access_token}}"
          },
          "settings": {
            "renderRequestBody": true,
            "encodeUrl": true,
            "followRedirects": "global",
            "cookies": {
              "send": true,
              "store": true
            },
            "rebuildPath": true
          }
        },
        {
          "url": "{{base_url}}/person/findByNumber/0664987654321",
          "name": "FindByPhoneNumber -> NOT FOUND",
          "meta": {
            "id": "req_6b1bf89f7d544b81b9f843fd782a5a84",
            "created": 1746500190372,
            "modified": 1746500190372,
            "isPrivate": false,
            "sortKey": -1746500187453
          },
          "method": "GET",
          "headers": [
            {
              "name": "User-Agent",
              "value": "insomnia/8.3.0"
            }
          ],
          "authentication": {
            "type": "bearer",
            "disabled": false,
            "token": "{{access_token}}"
          },
          "settings": {
            "renderRequestBody": true,
            "encodeUrl": true,
            "followRedirects": "global",
            "cookies": {
              "send": true,
              "store": true
            },
            "rebuildPath": true
          }
        },
        {
          "url": "{{base_url}}/person/search",
          "name": "FindByQuery",
          "meta": {
            "id": "req_b5ffe0bfbe1f495ca5ff4a14c9b9864c",
            "created": 1746500190372,
            "modified": 1746500190372,
            "isPrivate": false,
            "sortKey": -1746500187452
          },
          "method": "GET",
          "parameters": [
            {
              "name": "query",
              "value": "Max",
              "disabled": false
            }
          ],
          "authentication": {
            "type": "bearer",
            "disabled": false,
            "token": "{{access_token}}"
          },
          "settings": {
            "renderRequestBody": true,
            "encodeUrl": true,
            "followRedirects": "global",
            "cookies": {
              "send": true,
              "store": true
            },
            "rebuildPath": true
          }
        },
        {
          "url": "{{base_url}}/person",
          "name": "AddPerson",
          "meta": {
            "id": "req_898220b7a15941f2b71002203e87a575",
            "created": 1746500190373,
            "modified": 1746500190373,
            "isPrivate": false,
            "sortKey": -1746500187451
          },
          "method": "POST",
          "body": {
            "mimeType": "application/json",
            "text": "{\r\n    \"firstName\": \"John\",\r\n    \"lastName\": \"Doe\"\r\n}"
          },
          "headers": [
            {
              "name": "Content-Type",
              "value": "application/json"
            }
          ],
          "authentication": {
            "type": "bearer",
            "disabled": false,
            "token": "{{access_token}}"
          },
          "settings": {
            "renderRequestBody": true,
            "encodeUrl": true,
            "followRedirects": "global",
            "cookies": {
              "send": true,
              "store": true
            },
            "rebuildPath": true
          }
        },
        {
          "url": "localhost:8080/person/8a72a345-dd60-4231-8cdd-1190f37dca3a",
          "name": "UpdatePerson",
          "meta": {
            "id": "req_b83c3d03d1d04f5b90117fa957b056d4",
            "created": 1746500190373,
            "modified": 1746500190373,
            "isPrivate": false,
            "sortKey": -1746500187450
          },
          "method": "PUT",
          "body": {
            "mimeType": "application/json",
            "text": "{\r\n    \"firstName\": \"Jane\",\r\n    \"lastName\": \"Doe\"\r\n}"
          },
          "headers": [
            {
              "name": "Content-Type",
              "value": "application/json"
            }
          ],
          "authentication": {
            "type": "bearer",
            "disabled": false,
            "token": "{{access_token}}"
          },
          "settings": {
            "renderRequestBody": true,
            "encodeUrl": true,
            "followRedirects": "global",
            "cookies": {
              "send": true,
              "store": true
            },
            "rebuildPath": true
          }
        },
        {
          "url": "{{_['base_url']}}/person/8a72a345-dd60-4231-8cdd-1190f37dca3a/telephone",
          "name": "AddTelephone",
          "meta": {
            "id": "req_40008eaa73df40138f253fb48d2cb6f0",
            "created": 1746500190374,
            "modified": 1746500190374,
            "isPrivate": false,
            "sortKey": -1746500187449
          },
          "method": "PUT",
          "body": {
            "mimeType": "application/json",
            "text": "{\n\t\t\t\"countyCode\": \"DE\",\n\t\t\t\"number\": \"787845451212\"\n}"
          },
          "parameters": [
            {
              "disabled": true
            }
          ],
          "headers": [
            {
              "name": "Content-Type",
              "value": "application/json"
            },
            {
              "name": "User-Agent",
              "value": "insomnia/8.3.0"
            }
          ],
          "authentication": {
            "type": "bearer",
            "disabled": false,
            "token": "{{access_token}}"
          },
          "settings": {
            "renderRequestBody": true,
            "encodeUrl": true,
            "followRedirects": "global",
            "cookies": {
              "send": true,
              "store": true
            },
            "rebuildPath": true
          }
        },
        {
          "url": "{{_['base_url']}}/person/8a72a345-dd60-4231-8cdd-1190f37dca3a/delete",
          "name": "DeletePersonById",
          "meta": {
            "id": "req_f8fa32396ff842f091a285ea056f885d",
            "created": 1746500190374,
            "modified": 1746500190374,
            "isPrivate": false,
            "sortKey": -1746500187448
          },
          "method": "DELETE",
          "parameters": [
            {
              "disabled": true
            }
          ],
          "authentication": {
            "type": "bearer",
            "disabled": false,
            "token": "{{access_token}}"
          },
          "settings": {
            "renderRequestBody": true,
            "encodeUrl": true,
            "followRedirects": "global",
            "cookies": {
              "send": true,
              "store": true
            },
            "rebuildPath": true
          }
        },
        {
          "url": "{{base_url}}/auth/login",
          "name": "Login",
          "meta": {
            "id": "req_27161fe426fe48f29eaada728044ac5b",
            "created": 1746500190375,
            "modified": 1746500190375,
            "isPrivate": false,
            "sortKey": -1746500187446
          },
          "method": "POST",
          "body": {
            "mimeType": "application/json",
            "text": "{\r\n    \"userName\": \"admin\",\r\n    \"password\": \"password\"\r\n}"
          },
          "headers": [
            {
              "name": "Content-Type",
              "value": "application/json"
            }
          ],
          "settings": {
            "renderRequestBody": true,
            "encodeUrl": true,
            "followRedirects": "global",
            "cookies": {
              "send": true,
              "store": true
            },
            "rebuildPath": true
          }
        },
        {
          "url": "{{_['base_url']}}/person/7ede325f-11f3-4eca-bdc0-ae20ce841005/telephone/5ac58860-e20e-4ce3-a92b-95e42a80a8af/delete",
          "name": "DeletePersonTelephoneById",
          "meta": {
            "id": "req_436d4ce0167740eb8eaf1af16ee3ad47",
            "created": 1746500190375,
            "modified": 1746500190375,
            "isPrivate": false,
            "sortKey": -1746500187447
          },
          "method": "DELETE",
          "authentication": {
            "type": "bearer",
            "disabled": false,
            "token": "{{access_token}}"
          },
          "settings": {
            "renderRequestBody": true,
            "encodeUrl": true,
            "followRedirects": "global",
            "cookies": {
              "send": true,
              "store": true
            },
            "rebuildPath": true
          }
        },
        {
          "url": "{{base_url}}/auth/register",
          "name": "Register",
          "meta": {
            "id": "req_c57d41c5ec1646809744c4a315c06dda",
            "created": 1746500190376,
            "modified": 1746500190376,
            "isPrivate": false,
            "sortKey": -1746500187445
          },
          "method": "POST",
          "body": {
            "mimeType": "application/json",
            "text": "{\r\n    \"userName\": \"john_doe\",\r\n    \"password\": \"123456\",\r\n    \"role\": \"USER\"\r\n}"
          },
          "headers": [
            {
              "name": "Content-Type",
              "value": "application/json"
            }
          ],
          "settings": {
            "renderRequestBody": true,
            "encodeUrl": true,
            "followRedirects": "global",
            "cookies": {
              "send": true,
              "store": true
            },
            "rebuildPath": true
          }
        }
      ],
      "environment": {
        "base_url": "localhost:8080",
        "access_token": "eyJhbGciOiJIUzI1NiIsInR5cCI6IkpXVCJ9.eyJpc3MiOiJqYXZhLXBvYy1hcGkiLCJzdWIiOiJhZG1pbiIsImV4cCI6MTc0NjUwNjgxN30.PebD16umlL9KBYE2wTxDNAcT41IFICuj1QRy05tfMTQ"
      },
      "environmentPropertyOrder": {
        "&": [
          "base_url",
          "access_token"
        ]
      }
    }
  ],
  "cookieJar": {
    "name": "Default Jar",
    "meta": {
      "id": "jar_f168ed4b20104c3bb83e969bfdc19c6559fee17b",
      "created": 1746500190378,
      "modified": 1746500190378
    }
  },
  "environments": {
    "name": "Base Environment",
    "meta": {
      "id": "env_f168ed4b20104c3bb83e969bfdc19c6559fee17b",
      "created": 1746500190377,
      "modified": 1746500233346,
      "isPrivate": false
    },
    "data": {
      "base_url": "localhost:8080"
    }
  }
}